nrc_to_jpg/__init__.py
nrc_to_jpg/__main__.py
nrc_to_jpg/cli.py
nrc_to_jpg/constants.py
nrc_to_jpg/py.typed
nrc_to_jpg/utils.py
nrc_to_jpg-2024.6.0.dist-info/entry_points.txt
nrc_to_jpg-2024.6.0.dist-info/LICENSE
nrc_to_jpg-2024.6.0.dist-info/WHEEL
nrc_to_jpg-2024.6.0.dist-info/METADATA
nrc_to_jpg-2024.6.0.dist-info/RECORD
