Metadata-Version: 2.1
Name: nrc-to-jpg
Version: 2024.6.0
Summary: Save the NRC front page to a JPG image.
Keywords: 
Author-email: Steven van de Graaf <steven@vandegraaf.xyz>
Requires-Python: ~=3.8
Classifier: Development Status :: 4 - Beta
Classifier: Environment :: Console
Classifier: Intended Audience :: Developers
Classifier: License :: OSI Approved :: MIT License
Classifier: Programming Language :: Python
Classifier: Programming Language :: Python :: 3
Classifier: Programming Language :: Python :: 3.8
Classifier: Programming Language :: Python :: 3.9
Classifier: Programming Language :: Python :: 3.10
Classifier: Programming Language :: Python :: 3.11
Classifier: Programming Language :: Python :: 3.12
Classifier: Programming Language :: Python :: 3 :: Only
Classifier: Typing :: Typed
Requires-Dist: click
Requires-Dist: httpx
Requires-Dist: nrc-to-jpg[tests,docs] ; extra == "dev"
Requires-Dist: furo ; extra == "docs"
Requires-Dist: myst-parser ; extra == "docs"
Requires-Dist: sphinx ; extra == "docs"
Requires-Dist: sphinx-autobuild ; extra == "docs"
Requires-Dist: sphinx-copybutton ; extra == "docs"
Requires-Dist: sphinxext-opengraph ; extra == "docs"
Requires-Dist: pytest ; extra == "tests"
Project-URL: Changelog, https://nrc-to-jpg.readthedocs.io/en/stable/changelog.html
Project-URL: Documentation, https://nrc-to-jpg.readthedocs.io/en/stable/
Project-URL: Issue Tracker, https://github.com/sgraaf/nrc-to-jpg/issues
Project-URL: Source Code, https://github.com/sgraaf/nrc-to-jpg
Provides-Extra: dev
Provides-Extra: docs
Provides-Extra: tests
